Workbook

Sheet Inputs
A1: Price_per_user | B1: 1000
A2: Starting_users | B2: 50
A3: Growth_rate | B3: 0.1
A4: Churn_rate | B4: 0.05
A5: Variable_cost_pct | B5: 0.3
A6: Fixed_cost | B6: 50000
A7: Starting_cash | B7: 300000
A8: CAC | B8: 500
A9: Lifetime_months | B9: 12

Sheet Model
A1: Month | B1: M1 | C1: M2 | D1: M3 | E1: M4 | F1: M5 | G1: M6 | H1: M7 | I1: M8 | J1: M9 | K1: M10 | L1: M11 | M1: M12 | N1: M13 | O1: M14 | P1: M15 | Q1: M16 | R1: M17 | S1: M18 | T1: M19 | U1: M20 | V1: M21 | W1: M22 | X1: M23 | Y1: M24 | Z1: M25 | AA1: M26 | AB1: M27 | AC1: M28 | AD1: M29 | AE1: M30 | AF1: M31 | AG1: M32 | AH1: M33 | AI1: M34 | AJ1: M35 | AK1: M36
A2: Users | B2: =Inputs!B2 | C2: =B2*(1+Inputs!B3-Inputs!B4) | D2: =C2*(1+Inputs!B3-Inputs!B4) | E2: =D2*(1+Inputs!B3-Inputs!B4) | F2: =E2*(1+Inputs!B3-Inputs!B4) | G2: =F2*(1+Inputs!B3-Inputs!B4) | H2: =G2*(1+Inputs!B3-Inputs!B4) | I2: =H2*(1+Inputs!B3-Inputs!B4) | J2: =I2*(1+Inputs!B3-Inputs!B4) | K2: =J2*(1+Inputs!B3-Inputs!B4) | L2: =K2*(1+Inputs!B3-Inputs!B4) | M2: =L2*(1+Inputs!B3-Inputs!B4) | N2: =M2*(1+Inputs!B3-Inputs!B4) | O2: =N2*(1+Inputs!B3-Inputs!B4) | P2: =O2*(1+Inputs!B3-Inputs!B4) | Q2: =P2*(1+Inputs!B3-Inputs!B4) | R2: =Q2*(1+Inputs!B3-Inputs!B4) | S2: =R2*(1+Inputs!B3-Inputs!B4) | T2: =S2*(1+Inputs!B3-Inputs!B4) | U2: =T2*(1+Inputs!B3-Inputs!B4) | V2: =U2*(1+Inputs!B3-Inputs!B4) | W2: =V2*(1+Inputs!B3-Inputs!B4) | X2: =W2*(1+Inputs!B3-Inputs!B4) | Y2: =X2*(1+Inputs!B3-Inputs!B4) | Z2: =Y2*(1+Inputs!B3-Inputs!B4) | AA2: =Z2*(1+Inputs!B3-Inputs!B4) | AB2: =[2*(1+Inputs!B3-Inputs!B4) | AC2: =\2*(1+Inputs!B3-Inputs!B4) | AD2: =]2*(1+Inputs!B3-Inputs!B4) | AE2: =^2*(1+Inputs!B3-Inputs!B4) | AF2: =_2*(1+Inputs!B3-Inputs!B4) | AG2: =`2*(1+Inputs!B3-Inputs!B4) | AH2: =a2*(1+Inputs!B3-Inputs!B4) | AI2: =b2*(1+Inputs!B3-Inputs!B4) | AJ2: =c2*(1+Inputs!B3-Inputs!B4) | AK2: =d2*(1+Inputs!B3-Inputs!B4)
A3: Revenue | B3: =B2*Inputs!B1 | C3: =C2*Inputs!B1 | D3: =D2*Inputs!B1 | E3: =E2*Inputs!B1 | F3: =F2*Inputs!B1 | G3: =G2*Inputs!B1 | H3: =H2*Inputs!B1 | I3: =I2*Inputs!B1 | J3: =J2*Inputs!B1 | K3: =K2*Inputs!B1 | L3: =L2*Inputs!B1 | M3: =M2*Inputs!B1 | N3: =N2*Inputs!B1 | O3: =O2*Inputs!B1 | P3: =P2*Inputs!B1 | Q3: =Q2*Inputs!B1 | R3: =R2*Inputs!B1 | S3: =S2*Inputs!B1 | T3: =T2*Inputs!B1 | U3: =U2*Inputs!B1 | V3: =V2*Inputs!B1 | W3: =W2*Inputs!B1 | X3: =X2*Inputs!B1 | Y3: =Y2*Inputs!B1 | Z3: =Z2*Inputs!B1 | AA3: =[2*Inputs!B1 | AB3: =\2*Inputs!B1 | AC3: =]2*Inputs!B1 | AD3: =^2*Inputs!B1 | AE3: =_2*Inputs!B1 | AF3: =`2*Inputs!B1 | AG3: =a2*Inputs!B1 | AH3: =b2*Inputs!B1 | AI3: =c2*Inputs!B1 | AJ3: =d2*Inputs!B1 | AK3: =e2*Inputs!B1
A4: Cost | B4: =B3*Inputs!B5+Inputs!B6 | C4: =C3*Inputs!B5+Inputs!B6 | D4: =D3*Inputs!B5+Inputs!B6 | E4: =E3*Inputs!B5+Inputs!B6 | F4: =F3*Inputs!B5+Inputs!B6 | G4: =G3*Inputs!B5+Inputs!B6 | H4: =H3*Inputs!B5+Inputs!B6 | I4: =I3*Inputs!B5+Inputs!B6 | J4: =J3*Inputs!B5+Inputs!B6 | K4: =K3*Inputs!B5+Inputs!B6 | L4: =L3*Inputs!B5+Inputs!B6 | M4: =M3*Inputs!B5+Inputs!B6 | N4: =N3*Inputs!B5+Inputs!B6 | O4: =O3*Inputs!B5+Inputs!B6 | P4: =P3*Inputs!B5+Inputs!B6 | Q4: =Q3*Inputs!B5+Inputs!B6 | R4: =R3*Inputs!B5+Inputs!B6 | S4: =S3*Inputs!B5+Inputs!B6 | T4: =T3*Inputs!B5+Inputs!B6 | U4: =U3*Inputs!B5+Inputs!B6 | V4: =V3*Inputs!B5+Inputs!B6 | W4: =W3*Inputs!B5+Inputs!B6 | X4: =X3*Inputs!B5+Inputs!B6 | Y4: =Y3*Inputs!B5+Inputs!B6 | Z4: =Z3*Inputs!B5+Inputs!B6 | AA4: =[3*Inputs!B5+Inputs!B6 | AB4: =\3*Inputs!B5+Inputs!B6 | AC4: =]3*Inputs!B5+Inputs!B6 | AD4: =^3*Inputs!B5+Inputs!B6 | AE4: =_3*Inputs!B5+Inputs!B6 | AF4: =`3*Inputs!B5+Inputs!B6 | AG4: =a3*Inputs!B5+Inputs!B6 | AH4: =b3*Inputs!B5+Inputs!B6 | AI4: =c3*Inputs!B5+Inputs!B6 | AJ4: =d3*Inputs!B5+Inputs!B6 | AK4: =e3*Inputs!B5+Inputs!B6
A5: Profit | B5: =B3-B4 | C5: =C3-C4 | D5: =D3-D4 | E5: =E3-E4 | F5: =F3-F4 | G5: =G3-G4 | H5: =H3-H4 | I5: =I3-I4 | ... Z5: =Z3-Z4 | AA5: =[3-[4 | AB5: =\3-\4 | AC5: =]3-]4 | AD5: =^3-^4 | AE5: =_3-_4 | AF5: =`3-`4 | AG5: =a3-a4 | AH5: =b3-b4 | AI5: =c3-c4 | AJ5: =d3-d4 | AK5: =e3-e4
A6: Cash | B6: =Inputs!B7 + B5 | C6: =B6+C5 | D6: =C6+D5 | E6: =D6+E5 | F6: =E6+F5 | G6: =F6+G5 | H6: =G6+H5 | I6: =H6+I5 | J6: =I6+J5 | ... Z6: =Y6+Z5 | AA6: =Z6+[5 | AB6: =[6+\5 | AC6: =\6+]5 | AD6: =]6+^5 | AE6: =^6+_5 | AF6: =_6+`5 | AG6: =`6+a5 | AH6: =a6+b5 | AI6: =b6+c5 | AJ6: =c6+d5 | AK6: =d6+e5

Sheet Dashboard
A1: Summary
A3: Total Revenue | B3: =SUM(Model!B3:AK3)
A4: Total Profit | B4: =SUM(Model!B5:AK5)
A5: Final Cash | B5: =Model!AK6
